{
    "key": "taxonomy_691606dae2e36",
    "title": "Cat Megamenu",
    "menu_order": 0,
    "active": true,
    "taxonomy": "megamenu-cat",
    "object_type": [
        "megamenu"
    ],
    "advanced_configuration": 0,
    "import_source": "",
    "import_date": "",
    "labels": {
        "name": "Cat Megamenu",
        "singular_name": "Megamenu cat",
        "menu_name": "Megamenu",
        "all_items": "All Megamenu",
        "edit_item": "Edit Megamenu cat",
        "view_item": "View Megamenu cat",
        "update_item": "Update Megamenu cat",
        "add_new_item": "Add New Megamenu cat",
        "new_item_name": "New Megamenu cat Name",
        "parent_item": "Parent Megamenu cat",
        "parent_item_colon": "Parent Megamenu cat:",
        "search_items": "Search Megamenu",
        "most_used": "",
        "not_found": "No megamenu found",
        "no_terms": "No megamenu",
        "name_field_description": "",
        "slug_field_description": "",
        "parent_field_description": "",
        "desc_field_description": "",
        "filter_by_item": "Filter by megamenu cat",
        "items_list_navigation": "Megamenu list navigation",
        "items_list": "Megamenu list",
        "back_to_items": "← Go to megamenu",
        "item_link": "Megamenu cat Link",
        "item_link_description": "A link to a megamenu cat"
    },
    "description": "",
    "capabilities": {
        "manage_terms": "manage_categories",
        "edit_terms": "manage_categories",
        "delete_terms": "manage_categories",
        "assign_terms": "edit_posts"
    },
    "public": 1,
    "publicly_queryable": 1,
    "hierarchical": 1,
    "show_ui": 1,
    "show_in_menu": 1,
    "show_in_nav_menus": 1,
    "show_in_rest": 1,
    "rest_base": "",
    "rest_namespace": "wp\/v2",
    "rest_controller_class": "WP_REST_Terms_Controller",
    "show_tagcloud": 1,
    "show_in_quick_edit": 1,
    "show_admin_column": 0,
    "rewrite": {
        "permalink_rewrite": "taxonomy_key",
        "with_front": "1",
        "rewrite_hierarchical": "0"
    },
    "query_var": "post_type_key",
    "query_var_name": "",
    "default_term": {
        "default_term_enabled": "0"
    },
    "sort": 0,
    "meta_box": "default",
    "meta_box_cb": "",
    "meta_box_sanitize_cb": "",
    "modified": 1763051327
}
